source/__init__.py
source/_version.py
source/ah.py
source/access/__init__.py
source/access/commands.py
source/cluster/__init__.py
source/cluster/commands.py
source/common/__init__.py
source/common/commands.py
source/dataset/__init__.py
source/dataset/commands.py
source/datastream/__init__.py
source/datastream/commands.py
source/datastream/tags.csv
source/graph/__init__.py
source/graph/commands.py
source/hierarchy/__init__.py
source/hierarchy/commands.py
source/org/__init__.py
source/org/commands.py
source/permissions/__init__.py
source/permissions/commands.py
source/permissions/rules/__init__.py
source/permissions/rules/commands.py
source/permissions/selectors/__init__.py
source/permissions/selectors/commands.py
source/pipeline/__init__.py
source/pipeline/commands.py
source/takeout/__init__.py
source/takeout/export_all_data.py
source/template/__init__.py
source/template/commands.py
source/user/__init__.py
source/user/commands.py
source/utils/__init__.py
source/utils/util_methods.py
source/workflow/__init__.py
source/workflow/commands.py
tests/__init__.py
tests/data_test.csv
tests/properties.py
tests/test_asset_access.py
tests/test_cluster_command.py
tests/test_datasets_commands.py
tests/test_graph_commands.py
tests/test_help.py
tests/test_helper.py
tests/test_org_command.py
tests/test_pipeline_commands.py
tests/test_templates_commands.py
tests/test_user_commands.py
tests/test_workflow_commands.py
unify_cli-3.6.2.dist-info/LICENSE
unify_cli-3.6.2.dist-info/METADATA
unify_cli-3.6.2.dist-info/WHEEL
unify_cli-3.6.2.dist-info/entry_points.txt
unify_cli-3.6.2.dist-info/top_level.txt
unify_cli-3.6.2.dist-info/RECORD
