Metadata-Version: 2.1
Name: unify-cli
Version: 3.6.2
Summary: Element Unify command line tool
Home-page: https://github.com/ElementAnalytics/element-unify-cli
Author: Element Analytics
Author-email: platform@ean.io
Classifier: Programming Language :: Python :: 3
Classifier: Programming Language :: Python :: 3.7
Requires-Python: >=3
License-File: LICENSE
Requires-Dist: click
Requires-Dist: setuptools
Requires-Dist: unify-sdk
Requires-Dist: pandas
